smart_terminal/__init__.py
smart_terminal/main.py
smart_terminal/ai/__init__.py
smart_terminal/ai/learning_engine.py
smart_terminal/ai/suggestion_engine.py
smart_terminal/core/__init__.py
smart_terminal/core/command_builder.py
smart_terminal/core/command_executor.py
smart_terminal/core/command_mapper.py
smart_terminal/tests/__init__.py
smart_terminal/tests/test_basic.py
smart_terminal/tests/test_enhanced_features.py
smart_terminal/utils/__init__.py
smart_terminal/utils/config.py
smart_terminal/utils/shell_integration.py
smart_terminal_ai-2.0.2.dist-info/licenses/LICENSE
smart_terminal_ai-2.0.2.dist-info/METADATA
smart_terminal_ai-2.0.2.dist-info/WHEEL
smart_terminal_ai-2.0.2.dist-info/entry_points.txt
smart_terminal_ai-2.0.2.dist-info/top_level.txt
smart_terminal_ai-2.0.2.dist-info/RECORD
