Metadata-Version: 2.4
Name: smart-terminal-ai
Version: 2.0.2
Summary: AI-powered terminal assistant with natural language processing, git integration, system monitoring, and enhanced features
Home-page: https://github.com/yourusername/smart-terminal
Author: Your Name
Author-email: Your Name <your.email@example.com>
License: MIT
Project-URL: Homepage, https://github.com/yourusername/smart-terminal
Project-URL: Documentation, https://github.com/yourusername/smart-terminal#readme
Project-URL: Repository, https://github.com/yourusername/smart-terminal
Project-URL: Issues, https://github.com/yourusername/smart-terminal/issues
Keywords: terminal,ai,nlp,productivity,developer-tools
Classifier: Development Status :: 4 - Beta
Classifier: Intended Audience :: Developers
Classifier: License :: OSI Approved :: MIT License
Classifier: Operating System :: OS Independent
Classifier: Programming Language :: Python :: 3
Classifier: Programming Language :: Python :: 3.8
Classifier: Programming Language :: Python :: 3.9
Classifier: Programming Language :: Python :: 3.10
Classifier: Programming Language :: Python :: 3.11
Classifier: Programming Language :: Python :: 3.12
Classifier: Topic :: Software Development :: Libraries :: Python Modules
Classifier: Topic :: System :: Systems Administration
Classifier: Topic :: Utilities
Requires-Python: >=3.8
License-File: LICENSE
Requires-Dist: click>=8.0.0
Requires-Dist: rich>=12.0.0
Requires-Dist: prompt_toolkit>=3.0.0
Requires-Dist: requests>=2.25.0
Requires-Dist: psutil>=5.8.0
Requires-Dist: gitpython>=3.1.0
Requires-Dist: colorama>=0.4.4
Provides-Extra: dev
Requires-Dist: pytest>=7.0.0; extra == "dev"
Requires-Dist: black>=22.0.0; extra == "dev"
Requires-Dist: flake8>=4.0.0; extra == "dev"
Requires-Dist: mypy>=0.950; extra == "dev"
Dynamic: author
Dynamic: home-page
Dynamic: license-file
Dynamic: requires-python
